vulnmine/__init__.py
vulnmine/__main__.py
vulnmine/gbls.py
vulnmine/matchsft.py
vulnmine/matchven.py
vulnmine/ml.py
vulnmine/nvd.py
vulnmine/sccm.py
vulnmine/utils.py
vulnmine/vulnmine.py
vulnmine/vulns.py
vulnmine/plugins/plugin1.py
vulnmine/plugins/plugin1.pyc
vulnmine/plugins/plugin1.yapsy-plugin
vulnmine/plugins/plugin2.py
vulnmine/plugins/plugin2.pyc
vulnmine/plugins/plugin2.yapsy-plugin
vulnmine/vulnmine_data/label_software.csv
vulnmine/vulnmine_data/label_vendors.csv
vulnmine/vulnmine_data/logging.json
vulnmine/vulnmine_data/logging.json.example
vulnmine/vulnmine_data/s_vndr_stop_wds.csv
vulnmine/vulnmine_data/software_classif_trained_Rdm_Forest.pkl.z
vulnmine/vulnmine_data/vendor_classif_trained_Rdm_Forest.pkl.z
vulnmine/vulnmine_data/vulnmine_defaults.ini
vulnmine-1.0.5.dist-info/DESCRIPTION.rst
vulnmine-1.0.5.dist-info/METADATA
vulnmine-1.0.5.dist-info/RECORD
vulnmine-1.0.5.dist-info/WHEEL
vulnmine-1.0.5.dist-info/metadata.json
vulnmine-1.0.5.dist-info/top_level.txt
