Metadata-Version: 2.0
Name: vulnmine
Version: 1.0.5
Summary: Mine SCCM and NIST NVD for host vulnerability data
Home-page: https://github.com/lorgor/vulnmine
Author: Loren Gordon
Author-email: lgordon@lgsec.biz
License: GPLv3
Keywords: machine learning data mining vulnerability
Platform: UNKNOWN
Classifier: Development Status :: 4 - Beta
Classifier: Intended Audience :: Information Technology
Classifier: Topic :: Security
Classifier: License :: OSI Approved :: GNU General Public License v3 (GPLv3)
Classifier: Programming Language :: Python :: 2
Classifier: Programming Language :: Python :: 2.7
Requires-Dist: fuzzywuzzy
Requires-Dist: numpy
Requires-Dist: pandas
Requires-Dist: python-Levenshtein
Requires-Dist: requests
Requires-Dist: schedule
Requires-Dist: scikit-learn (==0.18.2)
Requires-Dist: scipy (==0.19.1)
Requires-Dist: sympy
Requires-Dist: xmltodict
Requires-Dist: yapsy
Provides-Extra: dev
Requires-Dist: check-manifest; extra == 'dev'
Provides-Extra: test
Requires-Dist: coverage; extra == 'test'
Requires-Dist: pytest; extra == 'test'
Requires-Dist: requests; extra == 'test'
Requires-Dist: responses; extra == 'test'
